{
  "dataset_revision": "ae001d0e6b1228650b7bd1c2c65fb50ad11a8aba",
  "task_name": "MTOPIntentClassification",
  "mteb_version": "1.38.1",
  "scores": {
    "validation": [
      {
        "accuracy": 0.588277,
        "f1": 0.404812,
        "f1_weighted": 0.616784,
        "scores_per_experiment": [
          {
            "accuracy": 0.525727,
            "f1": 0.370329,
            "f1_weighted": 0.550475
          },
          {
            "accuracy": 0.587025,
            "f1": 0.402778,
            "f1_weighted": 0.612925
          },
          {
            "accuracy": 0.634452,
            "f1": 0.422159,
            "f1_weighted": 0.663125
          },
          {
            "accuracy": 0.593736,
            "f1": 0.40255,
            "f1_weighted": 0.637023
          },
          {
            "accuracy": 0.575391,
            "f1": 0.405688,
            "f1_weighted": 0.609343
          },
          {
            "accuracy": 0.582998,
            "f1": 0.424442,
            "f1_weighted": 0.605321
          },
          {
            "accuracy": 0.578523,
            "f1": 0.394301,
            "f1_weighted": 0.605475
          },
          {
            "accuracy": 0.559284,
            "f1": 0.396552,
            "f1_weighted": 0.576702
          },
          {
            "accuracy": 0.604922,
            "f1": 0.398254,
            "f1_weighted": 0.634803
          },
          {
            "accuracy": 0.640716,
            "f1": 0.431069,
            "f1_weighted": 0.672653
          }
        ],
        "main_score": 0.588277,
        "hf_subset": "en",
        "languages": [
          "eng-Latn"
        ]
      },
      {
        "accuracy": 0.557906,
        "f1": 0.350758,
        "f1_weighted": 0.601537,
        "scores_per_experiment": [
          {
            "accuracy": 0.548209,
            "f1": 0.348813,
            "f1_weighted": 0.596274
          },
          {
            "accuracy": 0.560882,
            "f1": 0.369328,
            "f1_weighted": 0.608902
          },
          {
            "accuracy": 0.560331,
            "f1": 0.361627,
            "f1_weighted": 0.610043
          },
          {
            "accuracy": 0.550964,
            "f1": 0.334527,
            "f1_weighted": 0.585601
          },
          {
            "accuracy": 0.577961,
            "f1": 0.36162,
            "f1_weighted": 0.620009
          },
          {
            "accuracy": 0.53719,
            "f1": 0.348759,
            "f1_weighted": 0.567439
          },
          {
            "accuracy": 0.577961,
            "f1": 0.334588,
            "f1_weighted": 0.618905
          },
          {
            "accuracy": 0.572452,
            "f1": 0.351694,
            "f1_weighted": 0.619202
          },
          {
            "accuracy": 0.521212,
            "f1": 0.343009,
            "f1_weighted": 0.569724
          },
          {
            "accuracy": 0.571901,
            "f1": 0.35361,
            "f1_weighted": 0.619271
          }
        ],
        "main_score": 0.557906,
        "hf_subset": "de",
        "languages": [
          "deu-Latn"
        ]
      },
      {
        "accuracy": 0.583235,
        "f1": 0.375297,
        "f1_weighted": 0.624249,
        "scores_per_experiment": [
          {
            "accuracy": 0.555337,
            "f1": 0.366444,
            "f1_weighted": 0.5968
          },
          {
            "accuracy": 0.605763,
            "f1": 0.390915,
            "f1_weighted": 0.65384
          },
          {
            "accuracy": 0.630648,
            "f1": 0.391059,
            "f1_weighted": 0.665724
          },
          {
            "accuracy": 0.537001,
            "f1": 0.359027,
            "f1_weighted": 0.575751
          },
          {
            "accuracy": 0.588736,
            "f1": 0.357143,
            "f1_weighted": 0.616787
          },
          {
            "accuracy": 0.607728,
            "f1": 0.38444,
            "f1_weighted": 0.650684
          },
          {
            "accuracy": 0.586771,
            "f1": 0.386069,
            "f1_weighted": 0.626153
          },
          {
            "accuracy": 0.569745,
            "f1": 0.396393,
            "f1_weighted": 0.617161
          },
          {
            "accuracy": 0.552063,
            "f1": 0.361154,
            "f1_weighted": 0.604548
          },
          {
            "accuracy": 0.598559,
            "f1": 0.360326,
            "f1_weighted": 0.635044
          }
        ],
        "main_score": 0.583235,
        "hf_subset": "es",
        "languages": [
          "spa-Latn"
        ]
      },
      {
        "accuracy": 0.474382,
        "f1": 0.333552,
        "f1_weighted": 0.523105,
        "scores_per_experiment": [
          {
            "accuracy": 0.476221,
            "f1": 0.334005,
            "f1_weighted": 0.525386
          },
          {
            "accuracy": 0.489537,
            "f1": 0.342708,
            "f1_weighted": 0.534615
          },
          {
            "accuracy": 0.503488,
            "f1": 0.330537,
            "f1_weighted": 0.554967
          },
          {
            "accuracy": 0.492074,
            "f1": 0.331903,
            "f1_weighted": 0.534052
          },
          {
            "accuracy": 0.48383,
            "f1": 0.346512,
            "f1_weighted": 0.542245
          },
          {
            "accuracy": 0.521877,
            "f1": 0.351692,
            "f1_weighted": 0.56906
          },
          {
            "accuracy": 0.474318,
            "f1": 0.32183,
            "f1_weighted": 0.526406
          },
          {
            "accuracy": 0.438808,
            "f1": 0.323775,
            "f1_weighted": 0.481622
          },
          {
            "accuracy": 0.441344,
            "f1": 0.329503,
            "f1_weighted": 0.494611
          },
          {
            "accuracy": 0.422321,
            "f1": 0.323057,
            "f1_weighted": 0.468083
          }
        ],
        "main_score": 0.474382,
        "hf_subset": "fr",
        "languages": [
          "fra-Latn"
        ]
      },
      {
        "accuracy": 0.53007,
        "f1": 0.344229,
        "f1_weighted": 0.568386,
        "scores_per_experiment": [
          {
            "accuracy": 0.530318,
            "f1": 0.33893,
            "f1_weighted": 0.56496
          },
          {
            "accuracy": 0.483598,
            "f1": 0.330535,
            "f1_weighted": 0.506064
          },
          {
            "accuracy": 0.528827,
            "f1": 0.34558,
            "f1_weighted": 0.572695
          },
          {
            "accuracy": 0.54175,
            "f1": 0.355803,
            "f1_weighted": 0.588576
          },
          {
            "accuracy": 0.537276,
            "f1": 0.346296,
            "f1_weighted": 0.577876
          },
          {
            "accuracy": 0.530318,
            "f1": 0.362812,
            "f1_weighted": 0.58037
          },
          {
            "accuracy": 0.545229,
            "f1": 0.330378,
            "f1_weighted": 0.575357
          },
          {
            "accuracy": 0.512922,
            "f1": 0.331262,
            "f1_weighted": 0.56073
          },
          {
            "accuracy": 0.543738,
            "f1": 0.352757,
            "f1_weighted": 0.572514
          },
          {
            "accuracy": 0.54672,
            "f1": 0.347936,
            "f1_weighted": 0.584724
          }
        ],
        "main_score": 0.53007,
        "hf_subset": "hi",
        "languages": [
          "hin-Deva"
        ]
      },
      {
        "accuracy": 0.543447,
        "f1": 0.371844,
        "f1_weighted": 0.589266,
        "scores_per_experiment": [
          {
            "accuracy": 0.514662,
            "f1": 0.355708,
            "f1_weighted": 0.562752
          },
          {
            "accuracy": 0.574506,
            "f1": 0.372785,
            "f1_weighted": 0.617857
          },
          {
            "accuracy": 0.518851,
            "f1": 0.355564,
            "f1_weighted": 0.563033
          },
          {
            "accuracy": 0.519449,
            "f1": 0.366214,
            "f1_weighted": 0.572076
          },
          {
            "accuracy": 0.547576,
            "f1": 0.390929,
            "f1_weighted": 0.595827
          },
          {
            "accuracy": 0.520646,
            "f1": 0.355077,
            "f1_weighted": 0.572922
          },
          {
            "accuracy": 0.564931,
            "f1": 0.392383,
            "f1_weighted": 0.60711
          },
          {
            "accuracy": 0.559545,
            "f1": 0.379421,
            "f1_weighted": 0.606228
          },
          {
            "accuracy": 0.536206,
            "f1": 0.365652,
            "f1_weighted": 0.577727
          },
          {
            "accuracy": 0.578097,
            "f1": 0.384707,
            "f1_weighted": 0.617126
          }
        ],
        "main_score": 0.543447,
        "hf_subset": "th",
        "languages": [
          "tha-Thai"
        ]
      }
    ],
    "test": [
      {
        "accuracy": 0.578386,
        "f1": 0.405245,
        "f1_weighted": 0.606595,
        "scores_per_experiment": [
          {
            "accuracy": 0.524852,
            "f1": 0.385289,
            "f1_weighted": 0.54826
          },
          {
            "accuracy": 0.570907,
            "f1": 0.406059,
            "f1_weighted": 0.599384
          },
          {
            "accuracy": 0.621523,
            "f1": 0.423181,
            "f1_weighted": 0.649439
          },
          {
            "accuracy": 0.586183,
            "f1": 0.397585,
            "f1_weighted": 0.6285
          },
          {
            "accuracy": 0.560876,
            "f1": 0.408687,
            "f1_weighted": 0.593786
          },
          {
            "accuracy": 0.557456,
            "f1": 0.410469,
            "f1_weighted": 0.579579
          },
          {
            "accuracy": 0.581167,
            "f1": 0.400437,
            "f1_weighted": 0.606584
          },
          {
            "accuracy": 0.556772,
            "f1": 0.399061,
            "f1_weighted": 0.575326
          },
          {
            "accuracy": 0.605791,
            "f1": 0.410607,
            "f1_weighted": 0.638392
          },
          {
            "accuracy": 0.618331,
            "f1": 0.411078,
            "f1_weighted": 0.646697
          }
        ],
        "main_score": 0.578386,
        "hf_subset": "en",
        "languages": [
          "eng-Latn"
        ]
      },
      {
        "accuracy": 0.570668,
        "f1": 0.358673,
        "f1_weighted": 0.61582,
        "scores_per_experiment": [
          {
            "accuracy": 0.572837,
            "f1": 0.371875,
            "f1_weighted": 0.619742
          },
          {
            "accuracy": 0.559594,
            "f1": 0.363088,
            "f1_weighted": 0.611641
          },
          {
            "accuracy": 0.57481,
            "f1": 0.352673,
            "f1_weighted": 0.624732
          },
          {
            "accuracy": 0.551423,
            "f1": 0.345272,
            "f1_weighted": 0.591735
          },
          {
            "accuracy": 0.582981,
            "f1": 0.365224,
            "f1_weighted": 0.628691
          },
          {
            "accuracy": 0.538743,
            "f1": 0.350986,
            "f1_weighted": 0.570269
          },
          {
            "accuracy": 0.595097,
            "f1": 0.35422,
            "f1_weighted": 0.638484
          },
          {
            "accuracy": 0.600451,
            "f1": 0.365976,
            "f1_weighted": 0.648315
          },
          {
            "accuracy": 0.53339,
            "f1": 0.349534,
            "f1_weighted": 0.58278
          },
          {
            "accuracy": 0.597351,
            "f1": 0.367881,
            "f1_weighted": 0.641814
          }
        ],
        "main_score": 0.570668,
        "hf_subset": "de",
        "languages": [
          "deu-Latn"
        ]
      },
      {
        "accuracy": 0.557872,
        "f1": 0.333063,
        "f1_weighted": 0.606435,
        "scores_per_experiment": [
          {
            "accuracy": 0.543362,
            "f1": 0.328529,
            "f1_weighted": 0.586513
          },
          {
            "accuracy": 0.583389,
            "f1": 0.347231,
            "f1_weighted": 0.641001
          },
          {
            "accuracy": 0.616744,
            "f1": 0.351148,
            "f1_weighted": 0.656699
          },
          {
            "accuracy": 0.517345,
            "f1": 0.326559,
            "f1_weighted": 0.56422
          },
          {
            "accuracy": 0.56004,
            "f1": 0.329778,
            "f1_weighted": 0.598012
          },
          {
            "accuracy": 0.582722,
            "f1": 0.332395,
            "f1_weighted": 0.633079
          },
          {
            "accuracy": 0.540694,
            "f1": 0.331195,
            "f1_weighted": 0.593774
          },
          {
            "accuracy": 0.525684,
            "f1": 0.330769,
            "f1_weighted": 0.579529
          },
          {
            "accuracy": 0.544696,
            "f1": 0.325956,
            "f1_weighted": 0.598349
          },
          {
            "accuracy": 0.564043,
            "f1": 0.327067,
            "f1_weighted": 0.613173
          }
        ],
        "main_score": 0.557872,
        "hf_subset": "es",
        "languages": [
          "spa-Latn"
        ]
      },
      {
        "accuracy": 0.459474,
        "f1": 0.338807,
        "f1_weighted": 0.500583,
        "scores_per_experiment": [
          {
            "accuracy": 0.456624,
            "f1": 0.341274,
            "f1_weighted": 0.493904
          },
          {
            "accuracy": 0.467899,
            "f1": 0.332693,
            "f1_weighted": 0.505392
          },
          {
            "accuracy": 0.497651,
            "f1": 0.331202,
            "f1_weighted": 0.537842
          },
          {
            "accuracy": 0.475415,
            "f1": 0.347381,
            "f1_weighted": 0.512594
          },
          {
            "accuracy": 0.461322,
            "f1": 0.330584,
            "f1_weighted": 0.511279
          },
          {
            "accuracy": 0.512371,
            "f1": 0.360808,
            "f1_weighted": 0.558462
          },
          {
            "accuracy": 0.467899,
            "f1": 0.342191,
            "f1_weighted": 0.509854
          },
          {
            "accuracy": 0.423739,
            "f1": 0.339053,
            "f1_weighted": 0.460582
          },
          {
            "accuracy": 0.424992,
            "f1": 0.333087,
            "f1_weighted": 0.467517
          },
          {
            "accuracy": 0.406827,
            "f1": 0.329794,
            "f1_weighted": 0.448402
          }
        ],
        "main_score": 0.459474,
        "hf_subset": "fr",
        "languages": [
          "fra-Latn"
        ]
      },
      {
        "accuracy": 0.524131,
        "f1": 0.32891,
        "f1_weighted": 0.559513,
        "scores_per_experiment": [
          {
            "accuracy": 0.534959,
            "f1": 0.313558,
            "f1_weighted": 0.568045
          },
          {
            "accuracy": 0.470061,
            "f1": 0.301486,
            "f1_weighted": 0.485727
          },
          {
            "accuracy": 0.535676,
            "f1": 0.341411,
            "f1_weighted": 0.577527
          },
          {
            "accuracy": 0.535676,
            "f1": 0.334696,
            "f1_weighted": 0.582188
          },
          {
            "accuracy": 0.532807,
            "f1": 0.343217,
            "f1_weighted": 0.567922
          },
          {
            "accuracy": 0.537827,
            "f1": 0.339104,
            "f1_weighted": 0.583394
          },
          {
            "accuracy": 0.54213,
            "f1": 0.333356,
            "f1_weighted": 0.568548
          },
          {
            "accuracy": 0.508426,
            "f1": 0.322355,
            "f1_weighted": 0.554334
          },
          {
            "accuracy": 0.531373,
            "f1": 0.342557,
            "f1_weighted": 0.555342
          },
          {
            "accuracy": 0.51237,
            "f1": 0.317362,
            "f1_weighted": 0.552101
          }
        ],
        "main_score": 0.524131,
        "hf_subset": "hi",
        "languages": [
          "hin-Deva"
        ]
      },
      {
        "accuracy": 0.53953,
        "f1": 0.358787,
        "f1_weighted": 0.585287,
        "scores_per_experiment": [
          {
            "accuracy": 0.511392,
            "f1": 0.3559,
            "f1_weighted": 0.55895
          },
          {
            "accuracy": 0.581917,
            "f1": 0.370155,
            "f1_weighted": 0.629098
          },
          {
            "accuracy": 0.514286,
            "f1": 0.336243,
            "f1_weighted": 0.558484
          },
          {
            "accuracy": 0.517902,
            "f1": 0.357078,
            "f1_weighted": 0.570107
          },
          {
            "accuracy": 0.539602,
            "f1": 0.360316,
            "f1_weighted": 0.583776
          },
          {
            "accuracy": 0.504159,
            "f1": 0.340848,
            "f1_weighted": 0.55681
          },
          {
            "accuracy": 0.5783,
            "f1": 0.383395,
            "f1_weighted": 0.622137
          },
          {
            "accuracy": 0.56094,
            "f1": 0.37328,
            "f1_weighted": 0.607663
          },
          {
            "accuracy": 0.535262,
            "f1": 0.35593,
            "f1_weighted": 0.573129
          },
          {
            "accuracy": 0.551537,
            "f1": 0.354722,
            "f1_weighted": 0.59272
          }
        ],
        "main_score": 0.53953,
        "hf_subset": "th",
        "languages": [
          "tha-Thai"
        ]
      }
    ]
  },
  "evaluation_time": 92.48717522621155,
  "kg_co2_emissions": null
}